dagcli/__init__.py
dagcli/ai.py
dagcli/client.py
dagcli/config.py
dagcli/configs.py
dagcli/forwarder.py
dagcli/jobs.py
dagcli/messages.py
dagcli/orgs.py
dagcli/proxy.py
dagcli/publish.py
dagcli/root.py
dagcli/run.py
dagcli/sessions.py
dagcli/tasks.py
dagcli/tokens.py
dagcli/transformers.py
dagcli/ty.py
dagcli/utils.py
dagcli/vlt.py
dagcli/ws.py
dagcli/scripts/bash-preexec.sh
dagcli/scripts/bashrc
dagcli/scripts/dag.commonrc
dagcli/scripts/daglib.py
dagcli/scripts/zshrc
dagcli/vault/__init__.py
dagcli/vault/credentials.py
dagcli/vault/hostgroups.py
dagcli/vault/ips.py
dagcli/vault/keys.py
dagcli/vault/lib.py
dagcli/vault/roles.py
dagcli/vault/root.py
dagcli/vault/urls.py
dagcli/vault/users.py
dagcli/vault/utils.py
dagknows-0.0.121.dist-info/licenses/LICENSE
dagknows-0.0.121.dist-info/METADATA
dagknows-0.0.121.dist-info/WHEEL
dagknows-0.0.121.dist-info/entry_points.txt
dagknows-0.0.121.dist-info/top_level.txt
dagknows-0.0.121.dist-info/zip-safe
dagknows-0.0.121.dist-info/RECORD
