Metadata-Version: 2.4
Name: dagknows
Version: 0.0.121
Summary: Our CLI utilities for DagKnows
Home-page: https://github.com/dagknows/dagclis
Author: Sriram Panyam
Author-email: sri@dagknows.com
License: BSD 3-Clause License
Keywords: dagknows,cli,api,setuptools
Classifier: License :: OSI Approved :: BSD License
Classifier: Programming Language :: Python :: 3
License-File: LICENSE
Requires-Dist: requests
Requires-Dist: boltons
Requires-Dist: psutil
Requires-Dist: pyyaml
Requires-Dist: hvac
Requires-Dist: typer[all]
Requires-Dist: marko
Requires-Dist: prompt_toolkit
Dynamic: license-file
